isy994/__init__.py
isy994/controller.py
isy994/soap_test.py
isy994/items/__init__.py
isy994/items/item_base.py
isy994/items/item_container.py
isy994/items/controller/__init__.py
isy994/items/controller/controller_base.py
isy994/items/controller/controller_container.py
isy994/items/devices/__init__.py
isy994/items/devices/device_container.py
isy994/items/devices/device_info.py
isy994/items/devices/common/__init__.py
isy994/items/devices/common/device_barrier.py
isy994/items/devices/common/device_base.py
isy994/items/devices/common/device_binary.py
isy994/items/devices/common/device_contact.py
isy994/items/devices/common/device_dimmer.py
isy994/items/devices/common/device_fan.py
isy994/items/devices/common/device_lock.py
isy994/items/devices/common/device_notification.py
isy994/items/devices/common/device_power.py
isy994/items/devices/common/device_speed_controller.py
isy994/items/devices/common/device_switch.py
isy994/items/devices/common/device_thermostat.py
isy994/items/devices/insteon/__init__.py
isy994/items/devices/insteon/device_insteon_base.py
isy994/items/devices/insteon/device_insteon_contact.py
isy994/items/devices/insteon/device_insteon_controller.py
isy994/items/devices/insteon/device_insteon_dimmer.py
isy994/items/devices/insteon/device_insteon_fan.py
isy994/items/devices/insteon/device_insteon_siren.py
isy994/items/devices/insteon/device_insteon_switch.py
isy994/items/devices/insteon/device_insteon_templinc.py
isy994/items/devices/insteon/insteon_device_manager.py
isy994/items/devices/zwave/__init__.py
isy994/items/devices/zwave/device_zwave_barrier.py
isy994/items/devices/zwave/device_zwave_base.py
isy994/items/devices/zwave/device_zwave_binary.py
isy994/items/devices/zwave/device_zwave_controller.py
isy994/items/devices/zwave/device_zwave_door_lock.py
isy994/items/devices/zwave/device_zwave_energy_meter.py
isy994/items/devices/zwave/device_zwave_notification.py
isy994/items/devices/zwave/device_zwave_on_off_power_switch.py
ISY994v5-0.9.7.dist-info/LICENSE
ISY994v5-0.9.7.dist-info/METADATA
ISY994v5-0.9.7.dist-info/WHEEL
ISY994v5-0.9.7.dist-info/top_level.txt
ISY994v5-0.9.7.dist-info/RECORD
