Metadata-Version: 2.1
Name: ISY994v5
Version: 0.9.7
Summary: ISY99 Controller Rest and Websocket client v5 firmware
Home-page: https://github.com/mjcumming/ISY994v5
Author: Michael Cumming
Author-email: mike@4831.com
License: UNKNOWN
Keywords: INSTEON,ISY994,ISY,Universal Devices
Platform: UNKNOWN
Classifier: Development Status :: 5 - Production/Stable
Classifier: Programming Language :: Python :: 3
Classifier: License :: OSI Approved :: MIT License
Classifier: Operating System :: OS Independent
License-File: LICENSE
Requires-Dist: aiohttp
